{
  "total": 52,
  "categories": [
    {
      "title": "dien_thoai_pho_thong",
      "viewurl": "https://nhattao.com/f/dien-thoai-pho-thong.572/"
    },
    {
      "title": "linh_kien_phu_kien_dien_thoai",
      "viewurl": "https://nhattao.com/f/linh-kien-phu-kien.547/"
    },
    {
      "title": "blackberry",
      "viewurl": "https://nhattao.com/f/blackberry.218/"
    },
    {
      "title": "dien_thoai_android",
      "viewurl": "https://nhattao.com/f/dien-thoai-android.544/"
    },
    { "title": "iphone", "viewurl": "https://nhattao.com/f/iphone.219/" },
    {
      "title": "windows_phone",
      "viewurl": "https://nhattao.com/f/windows-phone.545/"
    },
    {
      "title": "smartphone_khac",
      "viewurl": "https://nhattao.com/f/smartphone-khac.570/"
    },
    {
      "title": "may_tinh_bang_khac",
      "viewurl": "https://nhattao.com/f/may-tinh-bang-khac.551/"
    },
    {
      "title": "linh_kien_phu_kien_may_tinh_bang",
      "viewurl": "https://nhattao.com/f/linh-kien-phu-kien.552/"
    },
    { "title": "ipad", "viewurl": "https://nhattao.com/f/ipad.569/" },
    {
      "title": "may_tinh_bang_android",
      "viewurl": "https://nhattao.com/f/may-tinh-bang-android.549/"
    },
    {
      "title": "may_tinh_bang_windows",
      "viewurl": "https://nhattao.com/f/may-tinh-bang-windows.550/"
    },
    {
      "title": "may_tinh_windows",
      "viewurl": "https://nhattao.com/f/may-tinh-windows.145/"
    },
    {
      "title": "may_tinh_apple",
      "viewurl": "https://nhattao.com/f/may-tinh-apple.483/"
    },
    {
      "title": "may_tinh_chrome_os",
      "viewurl": "https://nhattao.com/f/may-tinh-chrome-os.582/"
    },
    {
      "title": "server_workstation",
      "viewurl": "https://nhattao.com/f/server-workstation.554/"
    },
    {
      "title": "linh_kien_u0026_phu_kien",
      "viewurl": "https://nhattao.com/f/linh-kien-phu-kien.555/"
    },
    {
      "title": "man_hinh_may_vi_tinh",
      "viewurl": "https://nhattao.com/f/man-hinh-may-vi-tinh.641/"
    },
    {
      "title": "dong_ho_thong_minh",
      "viewurl": "https://nhattao.com/f/dong-ho-thong-minh.585/"
    },
    {
      "title": "dong_ho_dien_tu",
      "viewurl": "https://nhattao.com/f/dong-ho-dien-tu.747/"
    },
    {
      "title": "dong_ho_thoi_trang",
      "viewurl": "https://nhattao.com/f/dong-ho-thoi-trang.748/"
    },
    {
      "title": "phu_kien_dong_ho",
      "viewurl": "https://nhattao.com/f/phu-kien-dong-ho.753/"
    },
    {
      "title": "may_anh_dslr",
      "viewurl": "https://nhattao.com/f/may-anh-dslr.571/"
    },
    {
      "title": "may_anh_compact",
      "viewurl": "https://nhattao.com/f/may-anh-compact.557/"
    },
    {
      "title": "may_anh_mirrorless",
      "viewurl": "https://nhattao.com/f/may-anh-mirrorless.558/"
    },
    {
      "title": "may_quay_phim",
      "viewurl": "https://nhattao.com/f/may-quay-phim.559/"
    },
    { "title": "ong_kinh", "viewurl": "https://nhattao.com/f/ong-kinh.560/" },
    {
      "title": "phu_kien_camera",
      "viewurl": "https://nhattao.com/f/phu-kien-camera.561/"
    },
    { "title": "flycam", "viewurl": "https://nhattao.com/f/flycam.731/" },
    { "title": "nghe_nhin", "viewurl": "https://nhattao.com/f/nghe-nhin.647/" },
    {
      "title": "may_moc_cong_nghiep",
      "viewurl": "https://nhattao.com/f/may-moc-cong-nghiep.759/"
    },
    {
      "title": "an_ninh_an_toan",
      "viewurl": "https://nhattao.com/f/an-ninh-an-toan.683/"
    },
    { "title": "dien_co", "viewurl": "https://nhattao.com/f/dien-co.687/" },
    {
      "title": "thiet_bi_van_phong",
      "viewurl": "https://nhattao.com/f/thiet-bi-van-phong.695/"
    },
    { "title": "dien_lanh", "viewurl": "https://nhattao.com/f/dien-lanh.654/" },
    { "title": "nha_bep", "viewurl": "https://nhattao.com/f/nha-bep.660/" },
    { "title": "gia_dung", "viewurl": "https://nhattao.com/f/gia-dung.669/" },
    {
      "title": "suc_khoe_lam_dep",
      "viewurl": "https://nhattao.com/f/suc-khoe-lam-dep.675/"
    },
    { "title": "o_to", "viewurl": "https://nhattao.com/f/o-to.708/" },
    { "title": "xe_dap", "viewurl": "https://nhattao.com/f/xe-dap.538/" },
    {
      "title": "xe_dap/xe_may_dien",
      "viewurl": "https://nhattao.com/f/xe-dap-xe-may-dien.714/"
    },
    {
      "title": "xe_can_bang",
      "viewurl": "https://nhattao.com/f/xe-can-bang.715/"
    },
    {
      "title": "phu_tung_xe_may",
      "viewurl": "https://nhattao.com/f/phu-tung-xe-may.717/"
    },
    {
      "title": "phu_tung_xe_dap",
      "viewurl": "https://nhattao.com/f/phu-tung-xe-dap.584/"
    },
    {
      "title": "phu_tung_xe_dap_dien",
      "viewurl": "https://nhattao.com/f/phu-tung-xe-dap-dien.716/"
    },
    { "title": "xe_may", "viewurl": "https://nhattao.com/f/xe-may.704/" },
    {
      "title": "phu_tung_o_to",
      "viewurl": "https://nhattao.com/f/phu-tung-o-to.721/"
    },
    {
      "title": "sim_du_lieu_3g/4g_",
      "viewurl": "https://nhattao.com/f/sim-du-lieu-3g-4g.542/"
    },
    {
      "title": "sim_so_dep",
      "viewurl": "https://nhattao.com/f/sim-so-dep.214/"
    },
    {
      "title": "mat_kinh_thong_minh",
      "viewurl": "https://nhattao.com/f/mat-kinh-thong-minh.750/"
    },
    {
      "title": "mat_kinh_can_thi_/_vien_thi",
      "viewurl": "https://nhattao.com/f/mat-kinh-can-thi-vien-thi.751/"
    },
    {
      "title": "mat_kinh_thoi_trang",
      "viewurl": "https://nhattao.com/f/mat-kinh-thoi-trang.752/"
    }
  ]
}
